hangul_utils/__init__.py
hangul_utils/banmal.py
hangul_utils/combine.py
hangul_utils/constant.py
hangul_utils/convert_key.py
hangul_utils/distance.py
hangul_utils/divide.py
hangul_utils/encode.py
hangul_utils/format_date.py
hangul_utils/format_number.py
hangul_utils/get_local.py
hangul_utils/includes_by_cho.py
hangul_utils/is_cho.py
hangul_utils/is_hangul.py
hangul_utils/is_jong.py
hangul_utils/is_jung.py
hangul_utils/josa.py
hangul_utils/normalize.py
hangul_utils/sort_hangul.py
hangul_utils/utils.py
py_hangul_utils-1.0.1.dist-info/LICENSE
py_hangul_utils-1.0.1.dist-info/METADATA
py_hangul_utils-1.0.1.dist-info/WHEEL
py_hangul_utils-1.0.1.dist-info/top_level.txt
py_hangul_utils-1.0.1.dist-info/RECORD
