Metadata-Version: 2.1
Name: py-hangul-utils
Version: 1.0.1
Summary: 한글 유틸 패키지
Home-page: https://github.com/Mineru98/py-hangul-utils
Author: iamiks
Author-email: mineru664500@gmail.com
Classifier: Programming Language :: Python :: 3
Classifier: License :: OSI Approved :: MIT License
Classifier: Operating System :: OS Independent
Requires-Python: >=3.8
License-File: LICENSE
